example_package_egortopshot/__init__.py
example_package_egortopshot/main.py
example_package_egortopshot/source.py
example_package_egortopshot-0.0.1.dist-info/METADATA
example_package_egortopshot-0.0.1.dist-info/WHEEL
example_package_egortopshot-0.0.1.dist-info/licenses/LICENSE
example_package_egortopshot-0.0.1.dist-info/RECORD
