Metadata-Version: 2.1
Name: example_package_egortopshot
Version: 0.0.1
Summary: A small example package
Project-URL: Homepage, https://github.com/egortopshot/example_package_egortopshot
Project-URL: Repository, https://github.com/egortopshot/example_package_egortopshot.git
Project-URL: Source, https://github.com/egortopshot/example_package_egortopshot
Author-email: egortopshot <egortopshot@gmail.com>
License-File: LICENSE
Classifier: License :: OSI Approved :: MIT License
Classifier: Operating System :: OS Independent
Classifier: Programming Language :: Python :: 3
Requires-Python: >=3.8
Requires-Dist: requests
